gpt_commit/__init__.py
gpt_commit/cli_parser.py
gpt_commit/diff_utils.py
gpt_commit/git_utils.py
gpt_commit/gpt_commit.py
gpt_commit/openai_utils.py
gpt_commit-0.1.2.dist-info/LICENSE
gpt_commit-0.1.2.dist-info/METADATA
gpt_commit-0.1.2.dist-info/WHEEL
gpt_commit-0.1.2.dist-info/entry_points.txt
gpt_commit-0.1.2.dist-info/top_level.txt
gpt_commit-0.1.2.dist-info/RECORD
