Metadata-Version: 2.1
Name: gpt-commit
Version: 0.1.2
Summary: A command-line tool that intelligently generates commit messages based on staged file changes in Git using OpenAI's GPT.
Home-page: https://github.com/josenerydev/gpt-commit
Author: José Nery
Author-email: josenerydev@gmail.com
License: MIT
Classifier: Development Status :: 3 - Alpha
Classifier: Intended Audience :: Developers
Classifier: License :: OSI Approved :: MIT License
Classifier: Programming Language :: Python :: 3
Classifier: Programming Language :: Python :: 3.6
Classifier: Programming Language :: Python :: 3.7
Classifier: Programming Language :: Python :: 3.8
Classifier: Programming Language :: Python :: 3.9
License-File: LICENSE
Requires-Dist: openai
